iac_bootstrap/__init__.py
iac_bootstrap/generate.py
iac_bootstrap/infra_bootstrap.py
iac_bootstrap/infra_builder_terraform.py
iac_bootstrap/install_nginx.py
iac_bootstrap/remove_terraform.py
iac_bootstrap-1.0.4.dist-info/LICENSE
iac_bootstrap-1.0.4.dist-info/METADATA
iac_bootstrap-1.0.4.dist-info/WHEEL
iac_bootstrap-1.0.4.dist-info/top_level.txt
iac_bootstrap-1.0.4.dist-info/RECORD
