Metadata-Version: 2.1
Name: iac-bootstrap
Version: 1.0.4
Summary: Python package to automate deploiment of the infrastructures
Home-page: https://github.com/WeScale/iac-bootstrap.git
Author: mehdi kerbedj
Author-email: mehdi.kerbedj@wescale.fr
License: UNKNOWN
Platform: UNKNOWN
Classifier: Programming Language :: Python :: 3
Classifier: License :: OSI Approved :: GNU General Public License v3 (GPLv3)
Classifier: Operating System :: OS Independent
Requires-Python: >=3.6
